{"steps": [{"hl": [0, 0, 0, 5, 0.01], "cs1": [0, 0, 0, 0, 0.0], "cs2": [0, 0, 0, 0, 0.0], "cs3": [0, 0, 0, 0, 0.0], "cs4": [0, 0, 0, 0, 0.0], "cs5": [0, 0, 0, 0, 0.0], "hr": [0, 0, 0, 0, 0.0], "r224": [0, 0, 0, 0, 0.0], "r228": [0, 0, 0, 0, 0.0], "r232": [0, 0, 0, 0, 0.0], "w240": [1, 0, 0, 0, 0.0], "tl": [0, 0, 0, 0, 0.0], "r208": [0, 0, 0, 0, 0.0], "r212": [1, 0, 0, 0, 0.0], "r216": [0, 0, 0, 0, 0.0], "tr": [0, 0, 0, 0, 0.0]}, {"hl": [0, 0, 0, 5, 0.03], "cs1": [0, 0, 0, 5, 0.04], "cs2": [0, 0, 0, 0, 0.0], "cs3": [0, 0, 0, 0, 0.0], "cs4": [0, 0, 0, 0, 0.0], "cs5": [0, 0, 0, 0, 0.0], "hr": [0, 0, 0, 0, 0.0], "r224": [0, 0, 0, 0, 0.0], "r228": [0, 0, 0, 0, 0.0], "r232": [0, 0, 0, 0, 0.0], "w240": [1, 0, 0, 0, 0.0], "tl": [0, 0, 0, 0, 0.0], "r208": [0, 0, 0, 0, 0.0], "r212": [1, 0, 0, 0, 0.0], "r216": [0, 0, 0, 0, 0.0], "tr": [0, 0, 0, 0, 0.0]}, {"hl": [0, 0, 0, 5, 0.04], "cs1": [0, 0, 0, 5, 0.12], "cs2": [0, 0, 0, 5, 0.02], "cs3": [0, 0, 0, 0, 0.0], "cs4": [0, 0, 0, 0, 0.0], "cs5": [0, 0, 0, 0, 0.0], "hr": [0, 0, 0, 0, 0.0], "r224": [0, 0, 0, 0, 0.0], "r228": [0, 0, 0, 0, 0.0], "r232": [0, 0, 0, 0, 0.0], "w240": [1, 0, 0, 0, 0.0], "tl": [0, 0, 0, 0, 0.0], "r208": [0, 0, 0, 0, 0.0], "r212": [1, 0, 0, 0, 0.0], "r216": [0, 0, 0, 0, 0.0], "tr": [0, 0, 0, 0, 0.0]}, {"hl": [0, 0, 0, 5, 0.06], "cs1": [0, 0, 0, 5, 0.25], "cs2": [0, 0, 0, 5, 0.08], "cs3": [0, 0, 0, 5, 0.01], "cs4": [0, 0, 0, 0, 0.0], "cs5": [0, 0, 0, 0, 0.0], "hr": [0, 0, 0, 0, 0.0], "r224": [0, 0, 0, 0, 0.0], "r228": [0, 0, 0, 0, 0.0], "r232": [0, 0, 0, 0, 0.0], "w240": [1, 0, 0, 0, 0.0], "tl": [0, 0, 0, 0, 0.0], "r208": [0, 0, 0, 0, 0.0], "r212": [1, 0, 0, 0, 0.0], "r216": [0, 0, 0, 0, 0.0], "tr": [0, 0, 0, 0, 0.0]}, {"hl": [0, 0, 0, 5, 0.07], "cs1": [0, 0, 0, 5, 0.42], "cs2": [0, 0, 0, 0, 0.08], "cs3": [0, 0, 0, 0, 0.01], "cs4": [0, 0, 0, 0, 0.0], "cs5": [0, 0, 0, 0, 0.0], "hr": [0, 0, 0, 0, 0.0], "r224": [0, 0, 0, 5, 0.05], "r228": [0, 0, 0, 5, 0.02], "r232": [0, 0, 0, 5, 0.0], "w240": [1, 0, 0, 0, 0.0], "tl": [0, 0, 0, 0, 0.0], "r208": [0, 0, 0, 0, 0.0], "r212": [1, 0, 0, 0, 0.0], "r216": [0, 0, 0, 0, 0.0], "tr": [0, 0, 0, 0, 0.0]}]}